{
  "FileName": "ArGdWHYo95.mp4",
  "FilePath": "C:\\Users\\19031020\\Desktop\\videoRecord\\Screenshots\\2021-09\\ArGdWHYo95.mp4",
  "DateTime": "2021-09-07T08:34:43.3787411+08:00",
  "Type": "File",
  "Host": ""
},
{
  "FileName": "OkZPla6v0z.mp4",
  "FilePath": "C:\\Users\\19031020\\Desktop\\videoRecord\\Screenshots\\2021-09\\OkZPla6v0z.mp4",
  "DateTime": "2021-09-07T08:35:30.5132301+08:00",
  "Type": "File",
  "Host": ""
},
{
  "FileName": "8jLJBl5v74.mp4",
  "FilePath": "C:\\Users\\19031020\\Desktop\\videoRecord\\Screenshots\\2021-09\\8jLJBl5v74.mp4",
  "DateTime": "2021-09-07T08:46:30.2556352+08:00",
  "Type": "File",
  "Host": ""
},
{
  "FileName": "MxRuenD1hR.mp4",
  "FilePath": "C:\\Users\\19031020\\Desktop\\videoRecord\\Screenshots\\2021-09\\MxRuenD1hR.mp4",
  "DateTime": "2021-09-07T08:46:52.3146654+08:00",
  "Type": "File",
  "Host": ""
},
{
  "FileName": "fYIJq7kUtT.mp4",
  "FilePath": "C:\\Users\\19031020\\Desktop\\videoRecord\\Screenshots\\2021-09\\fYIJq7kUtT.mp4",
  "DateTime": "2021-09-07T09:18:46.0314652+08:00",
  "Type": "File",
  "Host": ""
},
{
  "FileName": "NumsnAXmcX.mp4",
  "FilePath": "C:\\Users\\19031020\\Desktop\\videoRecord\\Screenshots\\2021-09\\NumsnAXmcX.mp4",
  "DateTime": "2021-09-07T10:08:04.7663605+08:00",
  "Type": "File",
  "Host": ""
},
{
  "FileName": "BYnZ295BEj.mp4",
  "FilePath": "C:\\Users\\19031020\\Desktop\\videoRecord\\Screenshots\\2021-09\\BYnZ295BEj.mp4",
  "DateTime": "2021-09-08T07:47:32.0083143+08:00",
  "Type": "File",
  "Host": ""
},
{
  "FileName": "A5ulK0KERT.mp4",
  "FilePath": "C:\\Users\\19031020\\Desktop\\videoRecord\\Screenshots\\2021-09\\A5ulK0KERT.mp4",
  "DateTime": "2021-09-08T10:14:06.1743476+08:00",
  "Type": "File",
  "Host": ""
},
{
  "FileName": "YvO656b9wO.mp4",
  "FilePath": "C:\\Users\\19031020\\Desktop\\videoRecord\\Screenshots\\2021-09\\YvO656b9wO.mp4",
  "DateTime": "2021-09-09T10:02:26.254347+08:00",
  "Type": "File",
  "Host": ""
},
{
  "FileName": "fQG7cq2bq2.mp4",
  "FilePath": "C:\\Users\\19031020\\Desktop\\videoRecord\\Screenshots\\2021-09\\fQG7cq2bq2.mp4",
  "DateTime": "2021-09-10T09:24:02.7685173+08:00",
  "Type": "File",
  "Host": ""
},
{
  "FileName": "XfeGtJh3hy.png",
  "FilePath": "C:\\Users\\19031020\\Desktop\\videoRecord\\Screenshots\\2021-09\\XfeGtJh3hy.png",
  "DateTime": "2021-09-10T10:07:49.311379+08:00",
  "Type": "Image",
  "Host": ""
},
{
  "FileName": "ryDd6MLqaW.png",
  "FilePath": "C:\\Users\\19031020\\Desktop\\videoRecord\\Screenshots\\2021-09\\ryDd6MLqaW.png",
  "DateTime": "2021-09-10T10:07:54.0789553+08:00",
  "Type": "Image",
  "Host": ""
},
{
  "FileName": "dmDOVxC7Wl.png",
  "FilePath": "C:\\Users\\19031020\\Desktop\\videoRecord\\Screenshots\\2021-09\\dmDOVxC7Wl.png",
  "DateTime": "2021-09-10T10:08:03.9250936+08:00",
  "Type": "Image",
  "Host": ""
},
{
  "FileName": "gWnVENsoic.png",
  "FilePath": "C:\\Users\\19031020\\Desktop\\videoRecord\\Screenshots\\2021-09\\gWnVENsoic.png",
  "DateTime": "2021-09-10T10:08:06.9013155+08:00",
  "Type": "Image",
  "Host": ""
},
{
  "FileName": "WINWORD_BJe86yX0BX.png",
  "FilePath": "C:\\Users\\19031020\\Desktop\\videoRecord\\Screenshots\\2021-09\\WINWORD_BJe86yX0BX.png",
  "DateTime": "2021-09-10T14:04:52.2733484+08:00",
  "Type": "Image",
  "Host": ""
},
{
  "FileName": "kvIGQfT77U.mp4",
  "FilePath": "C:\\Users\\19031020\\Desktop\\videoRecord\\Screenshots\\2021-09\\kvIGQfT77U.mp4",
  "DateTime": "2021-09-15T09:49:35.5767472+08:00",
  "Type": "File",
  "Host": ""
}